LICENSE
MANIFEST.in
README.md
setup.cfg
setup.py
audesc/__init__.py
audesc/base.py
audesc/constants.py
audesc/describers.py
audesc/exceptions.py
audesc/format.py
audesc/utils.py
audesc.egg-info/PKG-INFO
audesc.egg-info/SOURCES.txt
audesc.egg-info/dependency_links.txt
audesc.egg-info/top_level.txt