Metadata-Version: 2.1
Name: audesc
Version: 0.0.5a0
Summary: a set of python modules to describe audios' meta data
Home-page: https://github.com/msalhab96/audesc
Maintainer: Mahmoud Salhab
License: MIT
Platform: UNKNOWN
License-File: LICENSE
